<?xml version="1.0" encoding="UTF-8"?>
<nifty xmlns="http://nifty-gui.sourceforge.net/nifty-1.3.xsd" xmlns:xsi="http://www.w3.org/2001/XMLSchema-instance">
    <useStyles filename="nifty-default-styles.xml" />
    <useStyles filename="Interface/DropDownStyle.xml" />
    <useStyles filename="Interface/ScrollbarStyle.xml" />
    <useStyles filename="Interface/ScrollpanelStyle.xml" />
    <useStyles filename="Interface/CheckBoxStyle.xml" />
    <useControls filename="nifty-default-controls.xml" />
    <useControls filename="Interface/MyControls.xml" />

    <!--<resourceBundle id="menu" filename="Interface/Texts/Text" />-->

    <registerSound id="buttonClick" filename="Sounds/Global/FE3D CLICK ON T.mp2" />
    <registerSound id="menuClick" filename="Sounds/Global/FE BUTTON BIG 5.mp2" />

    <style id="menuTextSmall">
        <attributes font="Interface/Fonts/Frontend20.fnt" color="#bbbcbb" />
    </style>
    <style id="menuText">
        <attributes font="Interface/Fonts/Frontend28.fnt" color="#bbbcbb" />
        <effect>
            <onHover name="textColorAnimated" start="#bbbcbb" end="#ffffff" />
            <onClick neverStopRendering="true" name="playSound" sound="menuClick"/>
        </effect>
    </style>
    <style id="menuTitleText">
        <attributes font="Interface/Fonts/Frontend28.fnt" color="#ff5f00" />
    </style>

    <style id="nifty-hiscore-head#text">
        <attributes font="Interface/Fonts/Frontend20.fnt" color="#ff5f00" />
    </style>
    <style id="nifty-hiscore-row#text">
        <attributes font="Interface/Fonts/Frontend20.fnt" color="#bbbcbb" />
    </style>

    <!-- +++++++++++++++++++++++++++++++++++++++ -->
    <!-- empty screen -->
    <!-- +++++++++++++++++++++++++++++++++++++++ -->
    <screen id="empty" controller="toniarts.openkeeper.game.state.MainMenuState">
        <layer id="layer" childLayout="vertical"></layer>
    </screen>

    <!-- +++++++++++++++++++++++++++++++++++++++ -->
    <!-- start screen -->
    <!-- +++++++++++++++++++++++++++++++++++++++ -->
    <screen id="start" controller="toniarts.openkeeper.game.state.MainMenuState">
        <layer id="layer" childLayout="vertical">
            <panel id="panel1" height="27.9%" width="100%" childLayout="vertical">
                <panel childLayout="center" align="center" valign="center">
                    <image filename="Textures/Logo.png" />
                </panel>
            </panel>
            <panel id="panel2" height="36.875%" width="100%" align="center" valign="center" childLayout="vertical" visibleToMouse="true">
                <panel childLayout="center" align="center" valign="center">
                    <text id="singlePlayer" style="menuText" text="${menu.71}">
                        <interact onClick="goToScreen(singlePlayer)" />
                    </text>
                </panel>
                <panel childLayout="center" align="center" valign="center">
                    <text id="multiplayer" style="menuText" text="${menu.72}">
                        <interact onClick="doTransition(271,multiplayer,273)" />
                    </text>
                </panel>
                <panel childLayout="center" align="center" valign="center">
                    <text id="mpd" style="menuText" text="${menu.1675}">
                        <interact onClick="doTransition(262,myPetDungeon,264)" />
                    </text>
                </panel>
            </panel>
            <panel id="panel3" height="7%" width="100%" align="center" valign="center" childLayout="center">

            </panel>
            <panel id="panel4" height="15.208%" width="100%" align="center" valign="top" childLayout="vertical" visibleToMouse="true">
                <panel childLayout="center" align="center" valign="top">
                    <text id="options" style="menuText" text="${menu.94}">
                        <interact onClick="doTransition(256,optionsMain,258)" />
                    </text>
                </panel>
                <panel childLayout="center" align="center" valign="top">
                    <text id="extras" style="menuText" text="${menu.73}">
                        <interact onClick="doTransition(259,extras,261)" />
                    </text>
                </panel>
            </panel>
            <panel id="panel5" height="5%" width="100%" align="center" valign="center" childLayout="vertical" visibleToMouse="true">
                <text id="quit" style="menuText" text="${menu.28}" align="center" valign="center">
                    <interact onClick="goToScreen(quitGame)" />
                </text>
            </panel>
            <panel id="panel6" height="*" width="100%" align="center" valign="top" childLayout="vertical">
                <panel childLayout="vertical" align="right" valign="top">
                    <text style="menuTextSmall" color="#bbbcbb" text="*PRE-ALPHA*"/>
                </panel>
                <panel childLayout="vertical" align="right" valign="top">
                    <text style="menuTextSmall" color="#bbbcbb" text="Open Source Edition"/>
                </panel>
            </panel>
        </layer>
    </screen>

    <!-- +++++++++++++++++++++++++++++++++++++++ -->
    <!-- single player game -->
    <!-- +++++++++++++++++++++++++++++++++++++++ -->
    <screen id="singlePlayer" controller="toniarts.openkeeper.game.state.MainMenuState">
        <layer id="layer" childLayout="vertical">
            <panel id="panel1" height="27.9%" width="100%" childLayout="vertical">
                <panel childLayout="center" align="center" valign="center">
                    <text id="singlePlayer" style="menuTitleText" text="${menu.71}" />
                </panel>
            </panel>
            <panel id="panel2" height="25%" width="100%" align="center" valign="center" childLayout="vertical" visibleToMouse="true">
                <panel childLayout="center" align="center" valign="center">
                    <text id="newCampaign" style="menuText" text="${menu.140}" />
                </panel>
                <panel childLayout="center" align="center" valign="center">
                    <text id="continueCampaign" style="menuText" text="${menu.2059}">
                        <interact onClick="doTransition(251,selectCampaignLevel,null)" />
                    </text>
                </panel>
            </panel>
            <panel id="panel3" height="5%" width="100%" align="center" valign="center" childLayout="center">

            </panel>
            <panel id="panel4" height="*" width="100%" align="center" valign="top" childLayout="vertical" visibleToMouse="true">
                <panel childLayout="center" align="center" valign="top">
                    <text id="skirmish" style="menuText" text="${menu.141}">
                        <interact onClick="doTransition(271,skirmish,273)" />
                    </text>
                </panel>
                <panel childLayout="center" align="center" valign="top">
                    <text id="loadGame" style="menuText" text="${menu.145}" />
                </panel>
            </panel>
            <panel childLayout="horizontal" align="right" valign="bottom">
                <control click="goToScreen(start)" id="back" name="cancelButton" />
                <text style="menuText" text="" width="48px" margin="5px" />
            </panel>
        </layer>
    </screen>

    <!-- +++++++++++++++++++++++++++++++++++++++ -->
    <!-- quit game -->
    <!-- +++++++++++++++++++++++++++++++++++++++ -->
    <screen id="quitGame" controller="toniarts.openkeeper.game.state.MainMenuState">
        <layer id="layer" childLayout="vertical">
            <panel id="panel1" height="40%" width="100%" childLayout="vertical">
                <panel height="100%" childLayout="center" align="center" valign="bottom">
                    <text id="singlePlayer" style="menuTitleText" text="${menu.28}" align="center" valign="bottom" />
                </panel>
            </panel>
            <panel id="panel2" height="*" width="100%" align="center" valign="center" childLayout="vertical" visibleToMouse="true">
                <panel childLayout="center" align="center" valign="center">
                    <text id="newCampaign" style="menuText" text="${menu.15}" />
                </panel>
            </panel>
            <panel childLayout="horizontal" align="right" valign="bottom">
                <control click="goToScreen(start)" id="back" name="cancelButton" />
                <control click="quitGame()" id="quit" name="okButton"/>
            </panel>
        </layer>
    </screen>

    <!-- +++++++++++++++++++++++++++++++++++++++ -->
    <!-- Campaign map, level selection -->
    <!-- +++++++++++++++++++++++++++++++++++++++ -->
    <screen id="selectCampaignLevel" controller="toniarts.openkeeper.game.state.MainMenuState">
        <layer id="layer" childLayout="vertical">
            <panel id="panel1" width="100%" childLayout="vertical">
            </panel>
            <panel childLayout="horizontal" align="right" valign="bottom">
                <control click="doTransition(252,singlePlayer,274)" id="back" name="cancelButton" />
                <text style="menuText" text="" width="48px" margin="5px" />
            </panel>
        </layer>
    </screen>

    <!-- +++++++++++++++++++++++++++++++++++++++ -->
    <!-- Campaign level briefing -->
    <!-- +++++++++++++++++++++++++++++++++++++++ -->
    <screen id="campaign" controller="toniarts.openkeeper.game.state.MainMenuState">
        <layer id="layer" childLayout="vertical">
            <panel id="panel1" width="100%" childLayout="vertical">
                <panel width="100%" childLayout="center" align="center" valign="center">
                    <text id="briefingTitle" style="menuTitleText" text="${menu.1476}" />
                </panel>
                <panel width="100%" childLayout="center" align="center" valign="center">
                    <control name="label" id="levelTitle" style="menuTitleText">
                    </control>
                </panel>
                <panel height="5%" width="100%" childLayout="center" align="center" valign="center">

                </panel>
                <!--Main objectives-->
                <panel height="30%" width="100%" childLayout="horizontal" align="center" valign="center">
                    <panel width="33%" childLayout="center" align="center" valign="center">
                        <image align="center" valign="top" id="mainObjectiveImage" width="144px" />
                    </panel>
                    <panel width="*" childLayout="vertical" align="left" valign="top">
                        <panel backgroundColor="#f508" width="100%" childLayout="vertical" paddingLeft="2%" marginBottom="2%">
                            <text align="left" valign="top" id="mainObjectivesTitle" style="menuTitleText" text="${menu.1408}" />
                        </panel>
                        <panel backgroundColor="#0008" width="100%" height="*" childLayout="vertical" paddingLeft="2%">
                            <control width="100%" name="label" style="menuTextSmall" id="mainObjective" textHAlign="left" textVAlign="top" wrap="true" />
                        </panel>
                    </panel>
                </panel>
                <panel height="3%" width="100%" childLayout="center" align="center" valign="center">

                </panel>
                <!--Subobjectives-->
                <panel height="*" id="subObjectivePanel" width="100%" childLayout="horizontal" align="center" valign="center">
                    <panel width="33%" childLayout="center" align="center" valign="center">
                        <image align="center" valign="top" id="subObjectiveImage" width="144px" />
                    </panel>
                    <panel width="*" childLayout="vertical" align="left" valign="top">
                        <panel backgroundColor="#f508" width="100%" childLayout="vertical" paddingLeft="2%" marginBottom="2%">
                            <text align="left" valign="top" id="subObjectivesTitle" style="menuTitleText" text="${menu.1409}" />
                        </panel>
                        <panel backgroundColor="#0008" width="100%" height="*" childLayout="vertical" paddingLeft="2%">
                            <panel width="100%" childLayout="vertical">
                                <control width="100%" name="label" style="menuTextSmall" id="subObjective1" textHAlign="left" textVAlign="top" wrap="true" />
                                <control width="100%" name="label" style="menuTextSmall" id="subObjective2" textHAlign="left" textVAlign="top" wrap="true" />
                                <control width="100%" name="label" style="menuTextSmall" id="subObjective3" textHAlign="left" textVAlign="top" wrap="true" />
                            </panel>
                        </panel>
                    </panel>
                </panel>
                <panel height="3%" width="100%" childLayout="center" align="center" valign="center">

                </panel>
            </panel>
            <panel childLayout="horizontal" align="right" valign="bottom">
                <control click="cancelLevelSelect()" id="back" name="cancelButton" />
                <control click="startCampaignLevel()" id="start" name="okButton" />
            </panel>
        </layer>
    </screen>

    <!-- +++++++++++++++++++++++++++++++++++++++ -->
    <!-- Options, main selection -->
    <!-- +++++++++++++++++++++++++++++++++++++++ -->
    <screen id="optionsMain" controller="toniarts.openkeeper.game.state.MainMenuState">
        <layer id="layer" childLayout="vertical">
            <panel id="panel1" width="100%" childLayout="vertical">
                <panel width="100%" childLayout="center" align="center" valign="center">
                    <text id="optionsTitle" style="menuTitleText" text="${menu.94}" />
                </panel>
                <panel width="100%" height="*" childLayout="center" align="center" valign="center">
                    <panel width="100%" childLayout="vertical" align="center" valign="center">
                        <text id="optionsGraphics" style="menuText" text="${menu.96}" align="center">
                            <interact onClick="goToScreen(optionsGraphics)" />
                        </text>
                        <text id="optionsSound" style="menuText" text="${menu.95}" align="center" >
                            <interact onClick="goToScreen(optionsSound)" />
                        </text>
                        <text id="optionsControl" style="menuText" text="${menu.98}" align="center" >
                            <interact onClick="goToScreen(optionsControl)" />
                        </text>
                    </panel>
                </panel>
            </panel>
            <panel childLayout="horizontal" align="right" valign="bottom">
                <control click="doTransition(257,start,274)" id="back" name="okButton" />
            </panel>
        </layer>
    </screen>

    <!-- +++++++++++++++++++++++++++++++++++++++ -->
    <!-- Graphic options -->
    <!-- +++++++++++++++++++++++++++++++++++++++ -->
    <screen id="optionsGraphics" controller="toniarts.openkeeper.game.state.MainMenuState">
        <layer id="layer" childLayout="vertical">
            <panel id="panel1" width="100%" childLayout="vertical">
                <panel width="100%" childLayout="center" align="center" valign="center">
                    <text id="briefingTitle" style="menuTitleText" text="${menu.96}" />
                </panel>
                <panel width="100%" height="*" childLayout="center" align="center" valign="center">
                    <panel childLayout="horizontal" valign="center">
                        <!--Left side options panel-->
                        <panel childLayout="vertical" align="left" valign="top">
                            <panel align="left" valign="center" childLayout="vertical" padding="10px">
                                <text style="menuTextSmall" text="${menu.134}: " />
                                <control width="250px" name="dropDown" id="resolution" />
                            </panel>
                            <panel align="left" valign="center" childLayout="horizontal" padding="10px">
                                <control name="checkbox" id="fullscreen" />
                                <text style="menuTextSmall" text=" Fullscreen" />
                            </panel>
                            <panel align="left" valign="center" childLayout="vertical" padding="10px">
                                <text style="menuTextSmall" text="Antialiasing: " />
                                <control width="100px" name="dropDown" id="antialiasing" />
                            </panel>
                            <panel align="left" valign="center" childLayout="vertical" padding="10px">
                                <text style="menuTextSmall" text="OpenGL: " />
                                <control width="250px" name="dropDown" id="openGl" />
                            </panel>
                            <panel align="left" valign="center" childLayout="horizontal" padding="10px">
                                <control name="checkbox" id="ssao" />
                                <text style="menuTextSmall" text=" SSAO" />
                            </panel>
                        </panel>
                        <!--Right side options panel-->
                        <panel  childLayout="vertical" align="right" valign="top">
                            <panel align="left" valign="center" childLayout="vertical" padding="10px">
                                <text style="menuTextSmall" text="Refresh rate: " />
                                <control width="100px" name="dropDown" id="refreshRate" />
                            </panel>
                            <panel align="left" valign="center" childLayout="horizontal" padding="10px">
                                <control name="checkbox" id="verticalSync" />
                                <text style="menuTextSmall" text=" Vertical sync" />
                            </panel>
                            <panel align="left" valign="center" childLayout="vertical" padding="10px">
                                <text style="menuTextSmall" text="Anisotropic filtering: " />
                                <control width="100px" name="dropDown" id="anisotropicFiltering" />
                            </panel>
                        </panel>
                    </panel>
                </panel>
            </panel>
            <panel childLayout="horizontal" align="right" valign="bottom">
                <control click="goToScreen(optionsMain)" id="back" name="cancelButton" />
                <control click="applyGraphicsSettings()" id="start" name="okButton" />
            </panel>
        </layer>
    </screen>

    <!-- +++++++++++++++++++++++++++++++++++++++ -->
    <!-- Sound Options -->
    <!-- +++++++++++++++++++++++++++++++++++++++ -->
    <screen id="optionsSound" controller="toniarts.openkeeper.game.state.MainMenuState">
        <layer id="layer" childLayout="vertical">
            <panel id="panel1" width="100%" childLayout="vertical">
                <panel width="100%" childLayout="center" align="center" valign="center">
                    <text id="optionsSoundTitle" style="menuTitleText" text="${menu.95}" />
                </panel>
                <panel width="100%" height="*" childLayout="center" align="center" valign="center">
                    <text style="menuTextSmall" text="Not ready yet" />
                </panel>
            </panel>
            <panel childLayout="horizontal" align="right" valign="bottom">
                <control click="goToScreen(optionsMain)" id="back" name="cancelButton" />
                <control click="goToScreen(optionsMain)" id="start" name="okButton" />
            </panel>
        </layer>
    </screen>

    <!-- +++++++++++++++++++++++++++++++++++++++ -->
    <!-- Control Options -->
    <!-- +++++++++++++++++++++++++++++++++++++++ -->
    <screen id="optionsControl" controller="toniarts.openkeeper.game.state.MainMenuState">
        <layer childLayout="vertical">
            <panel width="90%" childLayout="vertical" align="center">
                <panel width="100%" childLayout="center" height="12%" align="center" valign="center">
                    <text id="optionsControlTitle" style="menuTitleText" text="${menu.98}" />
                </panel>
                
                <!--Spacer-->
                <panel height="5%" width="100%" align="center" valign="center" />                
            
                <panel width="100%" height="*" childLayout="vertical" align="center" valign="center">
                    <control id="keyboardSetup" name="table" vertical="optional" displayItems="5" selection="Single" 
                             colCount="2"
                             col0="${menu.2845};55;java.lang.String;#32050c30"
                             col1="${menu.2846};45;java.lang.String;#32050c30"
                    />
                </panel>
                
                <!--Spacer-->
                <panel height="5%" width="100%" align="center" valign="center" />        
                
                <panel align="center" valign="center" childLayout="horizontal" padding="10px,10px">
                    <panel childLayout="vertical" align="center" width="50%" padding="0px,20px,0px,20px">                        
                        <text style="menuTextSmall" text="${menu.1466}" width="100%" />     
                        <control id="mouseSensitivity" name="horizontalSlider" min="0.5" max="2" initial="0.7" stepSize="0.1" buttonStepSize="0.1"/>                        
                    </panel>
                    <panel childLayout="vertical" align="center" width="50%" padding="0px,20px,0px,20px">                        
                        <text style="menuTextSmall" text="${menu.1469}" width="100%" />
                        <control id="gameSpeed" name="horizontalSlider" min="0.25" max="4" initial="1.0" stepSize="0.25" buttonStepSize="0.25"/>
                    </panel>
                </panel>    
                
                <panel align="center" valign="center" childLayout="horizontal" padding="10px,10px">
                    <panel childLayout="horizontal" align="center" valign="bottom" width="50%" padding="0px,20px,0px,20px">                        
                        <control name="checkbox" id="invertMouse" />
                        <text style="menuTextSmall" text=" ${menu.2840}" />                                               
                    </panel>
                    <panel childLayout="vertical" align="center" width="50%" padding="0px,20px,0px,20px">
                        <text style="menuTextSmall" text="${menu.1468}" width="100%" />
                        <control id="scrollSpeed" name="horizontalSlider" min="0.25" max="4" initial="1.0" stepSize="0.25" buttonStepSize="0.25"/>
                    </panel>
                </panel> 
                
                <panel height="*" align="center" valign="center" />
               
            </panel>
            <panel childLayout="horizontal" align="right" valign="bottom">
                <control click="goToScreen(optionsMain)" id="back" name="cancelButton" />
                <control click="goToScreen(optionsMain)" id="start" name="okButton" />
            </panel>
        </layer>
    </screen>

    <!-- +++++++++++++++++++++++++++++++++++++++ -->
    <!-- Extras -->
    <!-- +++++++++++++++++++++++++++++++++++++++ -->
    <screen id="extras" controller="toniarts.openkeeper.game.state.MainMenuState">
        <layer id="layer" childLayout="vertical">
            <panel id="panel1" height="27.9%" width="100%" childLayout="vertical">
                <panel childLayout="center" align="center" valign="center">
                    <text id="extrasTitle" style="menuTitleText" text="${menu.73}" />
                </panel>
            </panel>
            <panel id="panel2" height="25%" width="100%" align="center" valign="center" childLayout="vertical" visibleToMouse="true">
                <panel childLayout="center" align="center" valign="center">
                    <text id="top" style="menuText" text="${menu.2802}">
                        <interact onClick="goToScreen(hiscores)" />
                    </text>
                </panel>
                <panel childLayout="center" align="center" valign="center">
                    <text id="movies" style="menuText" text="${menu.93}">
                        <interact onClick="goToScreen(movies)" />
                    </text>
                </panel>
            </panel>
            <panel id="panel3" height="5%" width="100%" align="center" valign="center" childLayout="center">

            </panel>
            <panel id="panel4" height="*" width="100%" align="center" valign="top" childLayout="vertical" visibleToMouse="true">
                <panel childLayout="center" align="center" valign="top">
                    <text id="trailer" style="menuText" text="${menu.86}">
                        <interact onClick="playMovie(trailer)" />
                    </text>
                </panel>
                <panel childLayout="center" align="center" valign="top">
                    <text id="credits" style="menuText" text="${menu.372}">
                        <interact onClick="doTransition(265,credits,null)" />
                    </text>
                </panel>
            </panel>
            <panel childLayout="vertical" align="right" valign="bottom">
                <control click="doTransition(260,start,274)" id="back" name="okButton" />
            </panel>
        </layer>
    </screen>

    <!-- +++++++++++++++++++++++++++++++++++++++ -->
    <!-- Top players -->
    <!-- +++++++++++++++++++++++++++++++++++++++ -->
    <screen id="hiscores" controller="toniarts.openkeeper.game.state.MainMenuState">
        <layer id="layer" childLayout="vertical">
            <panel id="panel1" height="20%" width="100%" childLayout="vertical">
                <panel childLayout="center" align="center" valign="center">
                    <text id="topTitle" style="menuTitleText" text="${menu.2802}" />
                </panel>
            </panel>

            <panel id="hiscoreList" height="*" width="100%" align="center" valign="center" childLayout="vertical" visibleToMouse="true">
                <!-- placeholder for hiscores -->
            </panel>

            <panel childLayout="vertical" align="right" valign="bottom">
                <control click="goToScreen(extras)" id="back" name="okButton" />
            </panel>
        </layer>
    </screen>

    <!-- +++++++++++++++++++++++++++++++++++++++ -->
    <!-- View Movies -->
    <!-- +++++++++++++++++++++++++++++++++++++++ -->
    <screen id="movies" controller="toniarts.openkeeper.game.state.MainMenuState">
        <layer id="layer" childLayout="vertical">
            <panel id="panel1" height="12%" width="100%" childLayout="vertical">
                <panel childLayout="center" align="center" valign="center">
                    <text id="moviesTitle" style="menuTitleText" text="${menu.93}" />
                </panel>
            </panel>


            <control id="moviePanel" name="scrollPanel" align="center" valign="center" horizontal="false" height="*" width="80%">
                <panel id="movieList" childLayout="vertical">
                    <!-- placeholder for movies -->
                </panel>
            </control>
            <panel childLayout="center" align="right" valign="bottom">
                <control click="goToScreen(extras)" id="back" name="okButton" />
            </panel>
        </layer>
    </screen>

    <!-- +++++++++++++++++++++++++++++++++++++++ -->
    <!-- Movie still locked message -->
    <!-- +++++++++++++++++++++++++++++++++++++++ -->
    <screen id="cutsceneLocked" controller="toniarts.openkeeper.game.state.MainMenuState">
        <layer id="layer" childLayout="vertical">
            <panel id="panel1" height="12%" width="100%" childLayout="vertical">
            </panel>
            <panel width="100%" height="*" childLayout="center" align="center" valign="center">
                <text width="80%" style="menuText" textAlign="center" text="${menu.2805}" wrap="true" />
            </panel>
            <panel childLayout="center" align="right" valign="bottom">
                <control click="goToScreen(movies)" id="back" name="okButton" />
            </panel>
        </layer>
    </screen>

    <!-- +++++++++++++++++++++++++++++++++++++++ -->
    <!-- Credits -->
    <!-- +++++++++++++++++++++++++++++++++++++++ -->
    <screen id="credits" controller="toniarts.openkeeper.game.state.MainMenuState">
        <layer id="layer" childLayout="vertical">
            <panel id="panel1" height="12%" width="100%" childLayout="vertical">
                <panel childLayout="center" align="center" valign="center">
                    <text id="creditsTitle" style="menuTitleText" text="${menu.372}" />
                </panel>
            </panel>
            <panel childClip="true" align="center" valign="center" childLayout="vertical" height="*" visibleToMouse="false">
                <panel id="creditList" width="60%" name="creditList" align="center" valign="center" childLayout="vertical">
                    <panel childLayout="vertical" width="100%" height="150%" />
                    <panel childLayout="horizontal" width="100%">
                        <text style="menuTextSmall" text="Colin Robinson" textHAlign="left" width="50%" />
                        <text style="menuTextSmall" text="${menu.2733}" textHAlign="right" width="50%"/>
                    </panel>
                    <panel childLayout="horizontal" width="100%">
                        <text style="menuTextSmall" text="Nick Goldsworthy" textHAlign="left" width="50%" />
                        <text style="menuTextSmall" text="${menu.377}" textHAlign="right" width="50%"/>
                    </panel>
                    <panel childLayout="horizontal" width="100%">
                        <text style="menuTextSmall" text="Pete Blow" textHAlign="left" width="50%" />
                        <text style="menuTextSmall" text="${menu.379}" textHAlign="right" width="50%"/>
                    </panel>
                    <panel childLayout="horizontal" width="100%">
                        <text style="menuTextSmall" text="Graham Harbour" textHAlign="left" width="50%" />
                        <text style="menuTextSmall" text="${menu.379}" textHAlign="right" width="50%"/>
                    </panel>
                    <panel childLayout="horizontal" width="100%">
                        <text style="menuTextSmall" text="Wayne Frost" textHAlign="left" width="50%" />
                        <text style="menuTextSmall" text="${menu.379}" textHAlign="right" width="50%"/>
                    </panel>
                    <panel childLayout="horizontal" width="100%">
                        <text style="menuTextSmall" text="Jon Lawrence" textHAlign="left" width="50%" />
                        <text style="menuTextSmall" text="${menu.2734}" textHAlign="right" width="50%"/>
                    </panel>
                    <text style="menuTextSmall" text="" width="100%" />
                    <panel childLayout="horizontal" width="100%">
                        <text style="menuTextSmall" text="Alex Peters" textHAlign="left" width="50%" />
                        <text style="menuTextSmall" text="${menu.381}" textHAlign="right" width="50%"/>
                    </panel>
                    <panel childLayout="horizontal" width="100%">
                        <text style="menuTextSmall" text="Martin Bell" textHAlign="left" width="50%" />
                        <text style="menuTextSmall" text="${menu.402}" textHAlign="right" width="50%"/>
                    </panel>
                    <panel childLayout="horizontal" width="100%">
                        <text style="menuTextSmall" text="Andy Cakebread" textHAlign="left" width="50%" />
                        <text style="menuTextSmall" text="${menu.380}" textHAlign="right" width="50%"/>
                    </panel>
                    <panel childLayout="horizontal" width="100%">
                        <text style="menuTextSmall" text="Paul Carpenter" textHAlign="left" width="50%" />
                        <text style="menuTextSmall" text="${menu.380}" textHAlign="right" width="50%"/>
                    </panel>
                    <panel childLayout="horizontal" width="100%">
                        <text style="menuTextSmall" text="Michael A Carr" textHAlign="left" width="50%" />
                        <text style="menuTextSmall" text="${menu.380}" textHAlign="right" width="50%"/>
                    </panel>
                    <panel childLayout="horizontal" width="100%">
                        <text style="menuTextSmall" text="Alex Dowdeswell" textHAlign="left" width="50%" />
                        <text style="menuTextSmall" text="${menu.380}" textHAlign="right" width="50%"/>
                    </panel>
                    <panel childLayout="horizontal" width="100%">
                        <text style="menuTextSmall" text="David Foskett" textHAlign="left" width="50%" />
                        <text style="menuTextSmall" text="${menu.380}" textHAlign="right" width="50%"/>
                    </panel>
                    <panel childLayout="horizontal" width="100%">
                        <text style="menuTextSmall" text="Colin Moore" textHAlign="left" width="50%" />
                        <text style="menuTextSmall" text="${menu.380}" textHAlign="right" width="50%"/>
                    </panel>
                    <panel childLayout="horizontal" width="100%">
                        <text style="menuTextSmall" text="Mark Stacey" textHAlign="left" width="50%" />
                        <text style="menuTextSmall" text="${menu.380}" textHAlign="right" width="50%"/>
                    </panel>
                    <panel childLayout="horizontal" width="100%">
                        <text style="menuTextSmall" text="Matthew Whitton" textHAlign="left" width="50%" />
                        <text style="menuTextSmall" text="${menu.380}" textHAlign="right" width="50%"/>
                    </panel>
                    <panel childLayout="horizontal" width="100%">
                        <text style="menuTextSmall" text="Thomas Anderson" textHAlign="left" width="50%" />
                        <text style="menuTextSmall" text="${menu.380}" textHAlign="right" width="50%"/>
                    </panel>
                    <panel childLayout="horizontal" width="100%">
                        <text style="menuTextSmall" text="Carsten Sorenson" textHAlign="left" width="50%" />
                        <text style="menuTextSmall" text="${menu.380}" textHAlign="right" width="50%"/>
                    </panel>
                    <panel childLayout="horizontal" width="100%">
                        <text style="menuTextSmall" text="Mark Huntley" textHAlign="left" width="50%" />
                        <text style="menuTextSmall" text="${menu.416}" textHAlign="right" width="50%"/>
                    </panel>
                    <panel childLayout="horizontal" width="100%">
                        <text style="menuTextSmall" text="Andy McDonald" textHAlign="left" width="50%" />
                        <text style="menuTextSmall" text="${menu.416}" textHAlign="right" width="50%"/>
                    </panel>
                    <panel childLayout="horizontal" width="100%">
                        <text style="menuTextSmall" text="Alistair Milne" textHAlign="left" width="50%" />
                        <text style="menuTextSmall" text="${menu.416}" textHAlign="right" width="50%"/>
                    </panel>
                    <panel childLayout="horizontal" width="100%">
                        <text style="menuTextSmall" text="Ian Shaw" textHAlign="left" width="50%" />
                        <text style="menuTextSmall" text="${menu.415}" textHAlign="right" width="50%"/>
                    </panel>
                    <panel childLayout="horizontal" width="100%">
                        <text style="menuTextSmall" text="Robin Green" textHAlign="left" width="50%" />
                        <text style="menuTextSmall" text="${menu.415}" textHAlign="right" width="50%"/>
                    </panel>
                    <panel childLayout="horizontal" width="100%">
                        <text style="menuTextSmall" text="Jarl Ostensen" textHAlign="left" width="50%" />
                        <text style="menuTextSmall" text="${menu.415}" textHAlign="right" width="50%"/>
                    </panel>
                    <panel childLayout="horizontal" width="100%">
                        <text style="menuTextSmall" text="Mark Feldman" textHAlign="left" width="50%" />
                        <text style="menuTextSmall" text="${menu.415}" textHAlign="right" width="50%"/>
                    </panel>
                    <panel childLayout="horizontal" width="100%">
                        <text style="menuTextSmall" text="Martin Griffiths" textHAlign="left" width="50%" />
                        <text style="menuTextSmall" text="${menu.2735}" textHAlign="right" wrap="true" width="50%"/>
                    </panel>
                    <panel childLayout="horizontal" width="100%">
                        <text style="menuTextSmall" text="Austin Ellis" textHAlign="left" width="50%" />
                        <text style="menuTextSmall" text="${menu.2737}" textHAlign="right" width="50%"/>
                    </panel>
                    <panel childLayout="horizontal" width="100%">
                        <text style="menuTextSmall" text="Mark Lamport" textHAlign="left" width="50%" />
                        <text style="menuTextSmall" text="${menu.385}" textHAlign="right" width="50%"/>
                    </panel>
                    <panel childLayout="horizontal" width="100%">
                        <text style="menuTextSmall" text="Andy Buchanan" textHAlign="left" width="50%" />
                        <text style="menuTextSmall" text="${menu.385}" textHAlign="right" width="50%"/>
                    </panel>
                    <text style="menuTextSmall" text="" width="100%" />
                    <panel childLayout="horizontal" width="100%">
                        <text style="menuTextSmall" text="David Amor" textHAlign="left" width="50%" />
                        <text style="menuTextSmall" text="${menu.2738}" textHAlign="right" width="50%"/>
                    </panel>
                    <panel childLayout="horizontal" width="100%">
                        <text style="menuTextSmall" text="Shintaro Kanaoya" textHAlign="left" width="50%" />
                        <text style="menuTextSmall" text="${menu.2739}" textHAlign="right" width="50%"/>
                    </panel>
                    <panel childLayout="horizontal" width="100%">
                        <text style="menuTextSmall" text="Julian Glover" textHAlign="left" width="50%" />
                        <text style="menuTextSmall" text="${menu.2740}" textHAlign="right" width="50%"/>
                    </panel>
                    <panel childLayout="horizontal" width="100%">
                        <text style="menuTextSmall" text="Shelagh Lewins" textHAlign="left" width="50%" />
                        <text style="menuTextSmall" text="${menu.2740}" textHAlign="right" width="50%"/>
                    </panel>
                    <panel childLayout="horizontal" width="100%">
                        <text style="menuTextSmall" text="Nick Ricks" textHAlign="left" width="50%" />
                        <text style="menuTextSmall" text="${menu.2740}" textHAlign="right" width="50%"/>
                    </panel>
                    <text style="menuTextSmall" text="" width="100%" />
                    <panel childLayout="horizontal" width="100%">
                        <text style="menuTextSmall" text="Sean Cooper" textHAlign="left" width="50%" />
                        <text style="menuTextSmall" text="${menu.2742}" textHAlign="right" width="50%"/>
                    </panel>
                    <panel childLayout="horizontal" width="100%">
                        <text style="menuTextSmall" text="Zy Nicholson" textHAlign="left" width="50%" />
                        <text style="menuTextSmall" text="${menu.374}" textHAlign="right" width="50%"/>
                    </panel>
                    <panel childLayout="horizontal" width="100%">
                        <text style="menuTextSmall" text="Alex Trowers" textHAlign="left" width="50%" />
                        <text style="menuTextSmall" text="${menu.374}" textHAlign="right" width="50%"/>
                    </panel>
                    <panel childLayout="horizontal" width="100%">
                        <text style="menuTextSmall" text="Andy Trowers" textHAlign="left" width="50%" />
                        <text style="menuTextSmall" text="${menu.374}" textHAlign="right" width="50%"/>
                    </panel>
                    <text style="menuTextSmall" text="" width="100%" />
                    <panel childLayout="horizontal" width="100%">
                        <text style="menuTextSmall" text="John Miles" textHAlign="left" width="50%" />
                        <text style="menuTextSmall" text="${menu.2743}" textHAlign="right" width="50%"/>
                    </panel>
                    <panel childLayout="horizontal" width="100%">
                        <text style="menuTextSmall" text="Jason Smith" textHAlign="left" width="50%" />
                        <text style="menuTextSmall" text="${menu.2744}" textHAlign="right" width="50%"/>
                    </panel>
                    <panel childLayout="horizontal" width="100%">
                        <text style="menuTextSmall" text="Adam Coglan" textHAlign="left" width="50%" />
                        <text style="menuTextSmall" text="${menu.2745}" textHAlign="right" width="50%"/>
                    </panel>
                    <panel childLayout="horizontal" width="100%">
                        <text style="menuTextSmall" text="Darren Pattenden" textHAlign="left" width="50%" />
                        <text style="menuTextSmall" text="${menu.388}" textHAlign="right" width="50%"/>
                    </panel>
                    <panel childLayout="horizontal" width="100%">
                        <text style="menuTextSmall" text="Peter Amachree" textHAlign="left" width="50%" />
                        <text style="menuTextSmall" text="${menu.388}" textHAlign="right" width="50%"/>
                    </panel>
                    <panel childLayout="horizontal" width="100%">
                        <text style="menuTextSmall" text="Kevin Duffy" textHAlign="left" width="50%" />
                        <text style="menuTextSmall" text="${menu.388}" textHAlign="right" width="50%"/>
                    </panel>
                    <panel childLayout="horizontal" width="100%">
                        <text style="menuTextSmall" text="Mike Man" textHAlign="left" width="50%" />
                        <text style="menuTextSmall" text="${menu.388}" textHAlign="right" width="50%"/>
                    </panel>
                    <panel childLayout="horizontal" width="100%">
                        <text style="menuTextSmall" text="Graham Bell" textHAlign="left" width="50%" />
                        <text style="menuTextSmall" text="${menu.2746}" textHAlign="right" width="50%"/>
                    </panel>
                    <text style="menuTextSmall" text="" width="100%" />
                    <panel childLayout="horizontal" width="100%">
                        <text style="menuTextSmall" text="Jason Lord" textHAlign="left" width="50%" />
                        <text style="menuTextSmall" text="${menu.2748}" textHAlign="right" width="50%"/>
                    </panel>
                    <panel childLayout="horizontal" width="100%">
                        <text style="menuTextSmall" text="Jamie Bradshaw" textHAlign="left" width="50%" />
                        <text style="menuTextSmall" text="${menu.2748}" textHAlign="right" width="50%"/>
                    </panel>
                    <text style="menuTextSmall" text="" width="100%" />
                    <panel childLayout="horizontal" width="100%">
                        <text style="menuTextSmall" text="Jon Weinbren" textHAlign="left" width="50%" />
                        <text style="menuTextSmall" text="${menu.2749}" textHAlign="right" width="50%"/>
                    </panel>
                    <panel childLayout="horizontal" width="100%">
                        <text style="menuTextSmall" text="Gordon Davidson" textHAlign="left" width="50%" />
                        <text style="menuTextSmall" text="${menu.2749}" textHAlign="right" width="50%"/>
                    </panel>
                    <text style="menuTextSmall" text="" width="100%" />
                    <panel childLayout="horizontal" width="100%">
                        <text style="menuTextSmall" text="Tracey Charlton" textHAlign="left" width="50%" />
                        <text style="menuTextSmall" text="${menu.2750}" textHAlign="right" width="50%"/>
                    </panel>
                    <text style="menuTextSmall" text="" width="100%" />
                    <panel childLayout="horizontal" width="100%">
                        <text style="menuTextSmall" text="Nick Laviers" textHAlign="left" width="50%" />
                        <text style="menuTextSmall" text="${menu.2751}" textHAlign="right" width="50%"/>
                    </panel>
                    <panel childLayout="horizontal" width="100%">
                        <text style="menuTextSmall" text="Matt Thurling" textHAlign="left" width="50%" />
                        <text style="menuTextSmall" text="${menu.401}" textHAlign="right" width="50%"/>
                    </panel>
                    <panel childLayout="horizontal" width="100%">
                        <text style="menuTextSmall" text="Adele Kellett" textHAlign="left" width="50%" />
                        <text style="menuTextSmall" text="${menu.401}" textHAlign="right" width="50%"/>
                    </panel>
                    <panel childLayout="horizontal" width="100%">
                        <text style="menuTextSmall" text="Elaine Williams" textHAlign="left" width="50%" />
                        <text style="menuTextSmall" text="${menu.401}" textHAlign="right" width="50%"/>
                    </panel>
                    <panel childLayout="horizontal" width="100%">
                        <text style="menuTextSmall" text="Mark Knight" textHAlign="left" width="50%" />
                        <text style="menuTextSmall" text="${menu.399}" textHAlign="right" width="50%"/>
                    </panel>
                    <panel childLayout="horizontal" width="100%">
                        <text style="menuTextSmall" text="Bill Lusty" textHAlign="left" width="50%" />
                        <text style="menuTextSmall" text="${menu.2753}" textHAlign="right" width="50%"/>
                    </panel>
                    <text style="menuTextSmall" text="" width="100%" />
                    <panel childLayout="horizontal" width="100%">
                        <text style="menuTextSmall" text="Andy Hamill" textHAlign="left" width="50%" />
                        <text style="menuTextSmall" text="${menu.2754}" textHAlign="right" width="50%"/>
                    </panel>
                    <panel childLayout="horizontal" width="100%">
                        <text style="menuTextSmall" text="Dan Farrant" textHAlign="left" width="50%" />
                        <text style="menuTextSmall" text="${menu.2755}" textHAlign="right" width="50%"/>
                    </panel>
                    <text style="menuTextSmall" text="" width="100%" />
                    <panel childLayout="horizontal" width="100%">
                        <text style="menuTextSmall" text="Richard Ridings" textHAlign="left" width="50%" />
                        <text style="menuTextSmall" text="${menu.2756}" textHAlign="right" width="50%"/>
                    </panel>
                    <panel childLayout="horizontal" width="100%">
                        <text style="menuTextSmall" text="Patrick Renwick" textHAlign="left" width="50%" />
                        <text style="menuTextSmall" text="${menu.2756}" textHAlign="right" width="50%"/>
                    </panel>
                    <panel childLayout="horizontal" width="100%">
                        <text style="menuTextSmall" text="Andrzej Butruk" textHAlign="left" width="50%" />
                        <text style="menuTextSmall" text="${menu.2756}" textHAlign="right" width="50%"/>
                    </panel>
                    <panel childLayout="horizontal" width="100%">
                        <text style="menuTextSmall" text="Peter Bolhuis" textHAlign="left" width="50%" />
                        <text style="menuTextSmall" text="${menu.2756}" textHAlign="right" width="50%"/>
                    </panel>
                    <text style="menuTextSmall" text="" width="100%" />
                    <panel childLayout="horizontal" width="100%">
                        <text style="menuTextSmall" text="Kate Harbour" textHAlign="left" width="50%" />
                        <text style="menuTextSmall" text="${menu.2757}" textHAlign="right" width="50%"/>
                    </panel>
                    <panel childLayout="horizontal" width="100%">
                        <text style="menuTextSmall" text="Gavin Robertson" textHAlign="left" width="50%" />
                        <text style="menuTextSmall" text="${menu.2757}" textHAlign="right" width="50%"/>
                    </panel>
                    <panel childLayout="horizontal" width="100%">
                        <text style="menuTextSmall" text="Nigel Carrington" textHAlign="left" width="50%" />
                        <text style="menuTextSmall" text="${menu.2757}" textHAlign="right" width="50%"/>
                    </panel>
                    <panel childLayout="horizontal" width="100%">
                        <text style="menuTextSmall" text="Patrick Borg" textHAlign="left" width="50%" />
                        <text style="menuTextSmall" text="${menu.2757}" textHAlign="right" width="50%"/>
                    </panel>
                    <panel childLayout="horizontal" width="100%">
                        <text style="menuTextSmall" text="Martine Meirhaeghe" textHAlign="left" width="50%" />
                        <text style="menuTextSmall" text="${menu.2757}" textHAlign="right" width="50%"/>
                    </panel>
                    <panel childLayout="horizontal" width="100%">
                        <text style="menuTextSmall" text="Michel Barbey" textHAlign="left" width="50%" />
                        <text style="menuTextSmall" text="${menu.2757}" textHAlign="right" width="50%"/>
                    </panel>
                    <panel childLayout="horizontal" width="100%">
                        <text style="menuTextSmall" text="Marloes van den Heuvel" textHAlign="left" width="50%" />
                        <text style="menuTextSmall" text="${menu.2757}" textHAlign="right" width="50%"/>
                    </panel>
                    <panel childLayout="horizontal" width="100%">
                        <text style="menuTextSmall" text="Bob de Graaff" textHAlign="left" width="50%" />
                        <text style="menuTextSmall" text="${menu.2757}" textHAlign="right" width="50%"/>
                    </panel>
                    <panel childLayout="horizontal" width="100%">
                        <text style="menuTextSmall" text="Marcel Maas" textHAlign="left" width="50%" />
                        <text style="menuTextSmall" text="${menu.2757}" textHAlign="right" width="50%"/>
                    </panel>
                    <panel childLayout="horizontal" width="100%">
                        <text style="menuTextSmall" text="Fred Meiier" textHAlign="left" width="50%" />
                        <text style="menuTextSmall" text="${menu.2757}" textHAlign="right" width="50%"/>
                    </panel>
                    <text style="menuTextSmall" text="" width="100%" />
                    <panel childLayout="horizontal" width="100%">
                        <text style="menuTextSmall" text="Nicholas Calderbank" textHAlign="left" width="50%" />
                        <text style="menuTextSmall" text="${menu.2758}" textHAlign="right" width="50%"/>
                    </panel>
                    <panel childLayout="horizontal" width="100%">
                        <text style="menuTextSmall" text="Richard Darbois" textHAlign="left" width="50%" />
                        <text style="menuTextSmall" text="${menu.2758}" textHAlign="right" width="50%"/>
                    </panel>
                    <panel childLayout="horizontal" width="100%">
                        <text style="menuTextSmall" text="Andrzej Butruk" textHAlign="left" width="50%" />
                        <text style="menuTextSmall" text="${menu.2758}" textHAlign="right" width="50%"/>
                    </panel>
                    <panel childLayout="horizontal" width="100%">
                        <text style="menuTextSmall" text="Bram Bart" textHAlign="left" width="50%" />
                        <text style="menuTextSmall" text="${menu.2758}" textHAlign="right" width="50%"/>
                    </panel>
                    <text style="menuTextSmall" text="" width="100%" />
                    <panel childLayout="horizontal" width="100%">
                        <text style="menuTextSmall" text="Lewis MacLeod" textHAlign="left" width="50%" />
                        <text style="menuTextSmall" text="${menu.2759}" textHAlign="right" width="50%"/>
                    </panel>
                    <panel childLayout="horizontal" width="100%">
                        <text style="menuTextSmall" text="Big Al" textHAlign="left" width="50%" />
                        <text style="menuTextSmall" text="${menu.2759}" textHAlign="right" width="50%"/>
                    </panel>
                    <panel childLayout="horizontal" width="100%">
                        <text style="menuTextSmall" text="Peter Amachree" textHAlign="left" width="50%" />
                        <text style="menuTextSmall" text="${menu.2759}" textHAlign="right" width="50%"/>
                    </panel>
                    <panel childLayout="horizontal" width="100%">
                        <text style="menuTextSmall" text="Dene Carter" textHAlign="left" width="50%" />
                        <text style="menuTextSmall" text="${menu.2759}" textHAlign="right" width="50%"/>
                    </panel>
                    <panel childLayout="horizontal" width="100%">
                        <text style="menuTextSmall" text="Ada Posta" textHAlign="left" width="50%" />
                        <text style="menuTextSmall" text="${menu.2759}" textHAlign="right" width="50%"/>
                    </panel>
                    <panel childLayout="horizontal" width="100%">
                        <text style="menuTextSmall" text="Andy Nyman" textHAlign="left" width="50%" />
                        <text style="menuTextSmall" text="${menu.2759}" textHAlign="right" width="50%"/>
                    </panel>
                    <panel childLayout="horizontal" width="100%">
                        <text style="menuTextSmall" text="James Taylor" textHAlign="left" width="50%" />
                        <text style="menuTextSmall" text="${menu.2759}" textHAlign="right" width="50%"/>
                    </panel>
                    <panel childLayout="horizontal" width="100%">
                        <text style="menuTextSmall" text="Ben Stevens" textHAlign="left" width="50%" />
                        <text style="menuTextSmall" text="${menu.2759}" textHAlign="right" width="50%"/>
                    </panel>
                    <panel childLayout="horizontal" width="100%">
                        <text style="menuTextSmall" text="Dirk Vojtilo" textHAlign="left" width="50%" />
                        <text style="menuTextSmall" text="${menu.407}" textHAlign="right" width="50%"/>
                    </panel>
                    <panel childLayout="horizontal" width="100%">
                        <text style="menuTextSmall" text="Katarzyna Gryglewska-Cebrat" textHAlign="left" width="50%" />
                        <text style="menuTextSmall" text="${menu.407}" textHAlign="right" width="50%"/>
                    </panel>
                    <panel childLayout="horizontal" width="100%">
                        <text style="menuTextSmall" text="Julio Valladares" textHAlign="left" width="50%" />
                        <text style="menuTextSmall" text="${menu.407}" textHAlign="right" width="50%"/>
                    </panel>
                    <panel childLayout="horizontal" width="100%">
                        <text style="menuTextSmall" text="Inger Marshall" textHAlign="left" width="50%" />
                        <text style="menuTextSmall" text="${menu.407}" textHAlign="right" width="50%"/>
                    </panel>
                    <text style="menuTextSmall" text="" width="100%" />
                    <panel childLayout="horizontal" width="100%">
                        <text style="menuTextSmall" text="Phuong Tran-Mai" textHAlign="left" width="50%" />
                        <text style="menuTextSmall" text="${menu.410}" textHAlign="right" width="50%"/>
                    </panel>
                    <panel childLayout="horizontal" width="100%">
                        <text style="menuTextSmall" text="Vincent Regnault" textHAlign="left" width="50%" />
                        <text style="menuTextSmall" text="${menu.410}" textHAlign="right" width="50%"/>
                    </panel>
                    <panel childLayout="horizontal" width="100%">
                        <text style="menuTextSmall" text="Nathalie Fernandez" textHAlign="left" width="50%" />
                        <text style="menuTextSmall" text="${menu.410}" textHAlign="right" width="50%"/>
                    </panel>
                    <panel childLayout="horizontal" width="100%">
                        <text style="menuTextSmall" text="Bianca Normann" textHAlign="left" width="50%" />
                        <text style="menuTextSmall" text="${menu.410}" textHAlign="right" width="50%"/>
                    </panel>
                    <panel childLayout="horizontal" width="100%">
                        <text style="menuTextSmall" text="C.T.O. S.p.A." textHAlign="left" width="50%" />
                        <text style="menuTextSmall" text="${menu.410}" textHAlign="right" width="50%"/>
                    </panel>
                    <panel childLayout="horizontal" width="100%">
                        <text style="menuTextSmall" text="Ricardo Martinez" textHAlign="left" width="50%" />
                        <text style="menuTextSmall" text="${menu.410}" textHAlign="right" width="50%"/>
                    </panel>
                    <panel childLayout="horizontal" width="100%">
                        <text style="menuTextSmall" text="Cristina Macia" textHAlign="left" width="50%" />
                        <text style="menuTextSmall" text="${menu.410}" textHAlign="right" width="50%"/>
                    </panel>
                    <panel childLayout="horizontal" width="100%">
                        <text style="menuTextSmall" text="U-TRAX Multi Media Productions" textHAlign="left" width="50%" />
                        <text style="menuTextSmall" text="${menu.410}" textHAlign="right" width="50%"/>
                    </panel>
                    <panel childLayout="horizontal" width="100%">
                        <text style="menuTextSmall" text="Magnus Jildestad" textHAlign="left" width="50%" />
                        <text style="menuTextSmall" text="${menu.410}" textHAlign="right" width="50%"/>
                    </panel>
                    <panel childLayout="horizontal" width="100%">
                        <text style="menuTextSmall" text="Ordhuset i Stockholm AB" textHAlign="left" width="50%" />
                        <text style="menuTextSmall" text="${menu.410}" textHAlign="right" width="50%"/>
                    </panel>
                    <panel childLayout="horizontal" width="100%">
                        <text style="menuTextSmall" text="Dicolai Hansen" textHAlign="left" width="50%" />
                        <text style="menuTextSmall" text="${menu.410}" textHAlign="right" width="50%"/>
                    </panel>
                    <panel childLayout="horizontal" width="100%">
                        <text style="menuTextSmall" text="Janusz Mrziogod" textHAlign="left" width="50%" />
                        <text style="menuTextSmall" text="${menu.410}" textHAlign="right" width="50%"/>
                    </panel>
                    <text style="menuTextSmall" text="" width="100%" />
                    <panel childLayout="horizontal" width="100%">
                        <text style="menuTextSmall" text="Lionel Berrodier" textHAlign="left" width="50%" />
                        <text style="menuTextSmall" text="${menu.406}" textHAlign="right" width="50%"/>
                    </panel>
                    <panel childLayout="horizontal" width="100%">
                        <text style="menuTextSmall" text="Giulio Marchionni" textHAlign="left" width="50%" />
                        <text style="menuTextSmall" text="${menu.406}" textHAlign="right" width="50%"/>
                    </panel>
                    <panel childLayout="horizontal" width="100%">
                        <text style="menuTextSmall" text="Sofia Engvall" textHAlign="left" width="50%" />
                        <text style="menuTextSmall" text="${menu.406}" textHAlign="right" width="50%"/>
                    </panel>
                    <panel childLayout="horizontal" width="100%">
                        <text style="menuTextSmall" text="Lars Berenbrinker" textHAlign="left" width="50%" />
                        <text style="menuTextSmall" text="${menu.406}" textHAlign="right" width="50%"/>
                    </panel>
                    <panel childLayout="horizontal" width="100%">
                        <text style="menuTextSmall" text="Antonio Yago" textHAlign="left" width="50%" />
                        <text style="menuTextSmall" text="${menu.406}" textHAlign="right" width="50%"/>
                    </panel>
                    <panel childLayout="horizontal" width="100%">
                        <text style="menuTextSmall" text="Alvaro Corral" textHAlign="left" width="50%" />
                        <text style="menuTextSmall" text="${menu.406}" textHAlign="right" width="50%"/>
                    </panel>
                    <panel childLayout="horizontal" width="100%">
                        <text style="menuTextSmall" text="U-TRAX Multi Media Productions" textHAlign="left" width="50%" />
                        <text style="menuTextSmall" text="${menu.406}" textHAlign="right" width="50%"/>
                    </panel>
                    <text style="menuTextSmall" text="" width="100%" />
                    <panel childLayout="horizontal" width="100%">
                        <text style="menuTextSmall" text="Kevin Donkin" textHAlign="left" width="50%" />
                        <text style="menuTextSmall" text="${menu.427}" textHAlign="right" width="50%"/>
                    </panel>
                    <panel childLayout="horizontal" width="100%">
                        <text style="menuTextSmall" text="Simon Handby" textHAlign="left" width="50%" />
                        <text style="menuTextSmall" text="${menu.427}" textHAlign="right" width="50%"/>
                    </panel>
                    <panel childLayout="horizontal" width="100%">
                        <text style="menuTextSmall" text="Daren Watson" textHAlign="left" width="50%" />
                        <text style="menuTextSmall" text="${menu.427}" textHAlign="right" width="50%"/>
                    </panel>
                    <text style="menuTextSmall" text="" width="100%" />
                    <panel childLayout="horizontal" width="100%">
                        <text style="menuTextSmall" text="Steven Lawrie" textHAlign="left" width="50%" />
                        <text style="menuTextSmall" text="${menu.398}" textHAlign="right" width="50%"/>
                    </panel>
                    <panel childLayout="horizontal" width="100%">
                        <text style="menuTextSmall" text="Darren Tuckey" textHAlign="left" width="50%" />
                        <text style="menuTextSmall" text="${menu.2762}" textHAlign="right" width="50%"/>
                    </panel>
                    <panel childLayout="horizontal" width="100%">
                        <text style="menuTextSmall" text="Lawrence Doyle" textHAlign="left" width="50%" />
                        <text style="menuTextSmall" text="${menu.2763}" textHAlign="right" width="50%"/>
                    </panel>
                    <text style="menuTextSmall" text="" width="100%" />
                    <panel childLayout="horizontal" width="100%">
                        <text style="menuTextSmall" text="Dan McDonald" textHAlign="left" width="50%" />
                        <text style="menuTextSmall" text="${menu.405}" textHAlign="right" width="50%"/>
                    </panel>
                    <panel childLayout="horizontal" width="100%">
                        <text style="menuTextSmall" text="Phil Mansell" textHAlign="left" width="50%" />
                        <text style="menuTextSmall" text="${menu.405}" textHAlign="right" width="50%"/>
                    </panel>
                    <panel childLayout="horizontal" width="100%">
                        <text style="menuTextSmall" text="Tristan Paramor" textHAlign="left" width="50%" />
                        <text style="menuTextSmall" text="${menu.405}" textHAlign="right" width="50%"/>
                    </panel>
                    <panel childLayout="horizontal" width="100%">
                        <text style="menuTextSmall" text="Andy Miller" textHAlign="left" width="50%" />
                        <text style="menuTextSmall" text="${menu.405}" textHAlign="right" width="50%"/>
                    </panel>
                    <panel childLayout="horizontal" width="100%">
                        <text style="menuTextSmall" text="Nathan Smethurst" textHAlign="left" width="50%" />
                        <text style="menuTextSmall" text="${menu.405}" textHAlign="right" width="50%"/>
                    </panel>
                    <panel childLayout="horizontal" width="100%">
                        <text style="menuTextSmall" text="Jez Harris" textHAlign="left" width="50%" />
                        <text style="menuTextSmall" text="${menu.405}" textHAlign="right" width="50%"/>
                    </panel>
                    <panel childLayout="horizontal" width="100%">
                        <text style="menuTextSmall" text="Robert Stevens" textHAlign="left" width="50%" />
                        <text style="menuTextSmall" text="${menu.405}" textHAlign="right" width="50%"/>
                    </panel>
                    <panel childLayout="horizontal" width="100%">
                        <text style="menuTextSmall" text="Ross Manton" textHAlign="left" width="50%" />
                        <text style="menuTextSmall" text="${menu.405}" textHAlign="right" width="50%"/>
                    </panel>
                    <panel childLayout="horizontal" width="100%">
                        <text style="menuTextSmall" text="Stuart Pratt" textHAlign="left" width="50%" />
                        <text style="menuTextSmall" text="${menu.405}" textHAlign="right" width="50%"/>
                    </panel>
                    <panel childLayout="horizontal" width="100%">
                        <text style="menuTextSmall" text="Braydon Burgess" textHAlign="left" width="50%" />
                        <text style="menuTextSmall" text="${menu.405}" textHAlign="right" width="50%"/>
                    </panel>
                    <panel childLayout="horizontal" width="100%">
                        <text style="menuTextSmall" text="Greg Williams" textHAlign="left" width="50%" />
                        <text style="menuTextSmall" text="${menu.405}" textHAlign="right" width="50%"/>
                    </panel>
                    <panel childLayout="horizontal" width="100%">
                        <text style="menuTextSmall" text="James Pickett" textHAlign="left" width="50%" />
                        <text style="menuTextSmall" text="${menu.405}" textHAlign="right" width="50%"/>
                    </panel>
                    <panel childLayout="horizontal" width="100%">
                        <text style="menuTextSmall" text="Ed Law" textHAlign="left" width="50%" />
                        <text style="menuTextSmall" text="${menu.405}" textHAlign="right" width="50%"/>
                    </panel>
                    <panel childLayout="horizontal" width="100%">
                        <text style="menuTextSmall" text="Martin Hall" textHAlign="left" width="50%" />
                        <text style="menuTextSmall" text="${menu.405}" textHAlign="right" width="50%"/>
                    </panel>
                    <panel childLayout="horizontal" width="100%">
                        <text style="menuTextSmall" text="John Brunton" textHAlign="left" width="50%" />
                        <text style="menuTextSmall" text="${menu.405}" textHAlign="right" width="50%"/>
                    </panel>
                    <panel childLayout="horizontal" width="100%">
                        <text style="menuTextSmall" text="Olly Burne" textHAlign="left" width="50%" />
                        <text style="menuTextSmall" text="${menu.405}" textHAlign="right" width="50%"/>
                    </panel>
                    <panel childLayout="horizontal" width="100%">
                        <text style="menuTextSmall" text="Darren King" textHAlign="left" width="50%" />
                        <text style="menuTextSmall" text="${menu.405}" textHAlign="right" width="50%"/>
                    </panel>
                    <panel childLayout="horizontal" width="100%">
                        <text style="menuTextSmall" text="Rob Charlish" textHAlign="left" width="50%" />
                        <text style="menuTextSmall" text="${menu.405}" textHAlign="right" width="50%"/>
                    </panel>
                    <panel childLayout="horizontal" width="100%">
                        <text style="menuTextSmall" text="Jeff Brutus" textHAlign="left" width="50%" />
                        <text style="menuTextSmall" text="${menu.405}" textHAlign="right" width="50%"/>
                    </panel>
                    <panel childLayout="horizontal" width="100%">
                        <text style="menuTextSmall" text="Stephen Harrison" textHAlign="left" width="50%" />
                        <text style="menuTextSmall" text="${menu.405}" textHAlign="right" width="50%"/>
                    </panel>
                    <panel childLayout="horizontal" width="100%">
                        <text style="menuTextSmall" text="Dominic Waddel" textHAlign="left" width="50%" />
                        <text style="menuTextSmall" text="${menu.405}" textHAlign="right" width="50%"/>
                    </panel>
                    <panel childLayout="horizontal" width="100%">
                        <text style="menuTextSmall" text="Idwal Wynne-Jones" textHAlign="left" width="50%" />
                        <text style="menuTextSmall" text="${menu.405}" textHAlign="right" width="50%"/>
                    </panel>
                    <panel childLayout="horizontal" width="100%">
                        <text style="menuTextSmall" text="Anthony Street" textHAlign="left" width="50%" />
                        <text style="menuTextSmall" text="${menu.405}" textHAlign="right" width="50%"/>
                    </panel>
                    <panel childLayout="horizontal" width="100%">
                        <text style="menuTextSmall" text="Anthony Pimentel" textHAlign="left" width="50%" />
                        <text style="menuTextSmall" text="${menu.405}" textHAlign="right" width="50%"/>
                    </panel>
                    <panel childLayout="horizontal" width="100%">
                        <text style="menuTextSmall" text="Samy Ben Romdhane" textHAlign="left" width="50%" />
                        <text style="menuTextSmall" text="${menu.405}" textHAlign="right" width="50%"/>
                    </panel>
                    <panel childLayout="horizontal" width="100%">
                        <text style="menuTextSmall" text="Ben Bryant" textHAlign="left" width="50%" />
                        <text style="menuTextSmall" text="${menu.405}" textHAlign="right" width="50%"/>
                    </panel>
                    <panel childLayout="horizontal" width="100%">
                        <text style="menuTextSmall" text="James Donovan" textHAlign="left" width="50%" />
                        <text style="menuTextSmall" text="${menu.405}" textHAlign="right" width="50%"/>
                    </panel>
                    <panel childLayout="horizontal" width="100%">
                        <text style="menuTextSmall" text="Richard Allen" textHAlign="left" width="50%" />
                        <text style="menuTextSmall" text="${menu.405}" textHAlign="right" width="50%"/>
                    </panel>
                    <panel childLayout="horizontal" width="100%">
                        <text style="menuTextSmall" text="Simon Smith" textHAlign="left" width="50%" />
                        <text style="menuTextSmall" text="${menu.405}" textHAlign="right" width="50%"/>
                    </panel>
                    <panel childLayout="horizontal" width="100%">
                        <text style="menuTextSmall" text="Nicolas Doucet" textHAlign="left" width="50%" />
                        <text style="menuTextSmall" text="${menu.405}" textHAlign="right" width="50%"/>
                    </panel>
                    <panel childLayout="horizontal" width="100%">
                        <text style="menuTextSmall" text="Julien Law" textHAlign="left" width="50%" />
                        <text style="menuTextSmall" text="${menu.405}" textHAlign="right" width="50%"/>
                    </panel>
                    <panel childLayout="horizontal" width="100%">
                        <text style="menuTextSmall" text="Nick Reigate" textHAlign="left" width="50%" />
                        <text style="menuTextSmall" text="${menu.405}" textHAlign="right" width="50%"/>
                    </panel>
                    <panel childLayout="horizontal" width="100%">
                        <text style="menuTextSmall" text="Karl Frazer" textHAlign="left" width="50%" />
                        <text style="menuTextSmall" text="${menu.405}" textHAlign="right" width="50%"/>
                    </panel>
                    <panel childLayout="horizontal" width="100%">
                        <text style="menuTextSmall" text="Mark Rose" textHAlign="left" width="50%" />
                        <text style="menuTextSmall" text="${menu.405}" textHAlign="right" width="50%"/>
                    </panel>
                    <panel childLayout="horizontal" width="100%">
                        <text style="menuTextSmall" text="James Harlow" textHAlign="left" width="50%" />
                        <text style="menuTextSmall" text="${menu.405}" textHAlign="right" width="50%"/>
                    </panel>
                    <panel childLayout="horizontal" width="100%">
                        <text style="menuTextSmall" text="Sarah Brooks-Fisher" textHAlign="left" width="50%" />
                        <text style="menuTextSmall" text="${menu.405}" textHAlign="right" width="50%"/>
                    </panel>
                    <panel childLayout="horizontal" width="100%">
                        <text style="menuTextSmall" text="Adam Phillips" textHAlign="left" width="50%" />
                        <text style="menuTextSmall" text="${menu.405}" textHAlign="right" width="50%"/>
                    </panel>
                    <text style="menuTextSmall" text="" width="100%" />
                    <panel childLayout="horizontal" width="100%">
                        <text style="menuTextSmall" text="Matt Price" textHAlign="left" width="50%" />
                        <text style="menuTextSmall" text="${menu.2766}" textHAlign="right" width="50%"/>
                    </panel>
                    <text style="menuTextSmall" text="" width="100%" />
                    <panel childLayout="horizontal" width="100%">
                        <text style="menuTextSmall" text="Owen O'Brien" textHAlign="left" width="50%" />
                        <text style="menuTextSmall" text="${menu.2767}" textHAlign="right" width="50%"/>
                    </panel>
                    <panel childLayout="horizontal" width="100%">
                        <text style="menuTextSmall" text="Patrick Buechner" textHAlign="left" width="50%" />
                        <text style="menuTextSmall" text="${menu.2768}" textHAlign="right" width="50%"/>
                    </panel>
                    <panel childLayout="horizontal" width="100%">
                        <text style="menuTextSmall" text="David Wilson" textHAlign="left" width="50%" />
                        <text style="menuTextSmall" text="${menu.2768}" textHAlign="right" width="50%"/>
                    </panel>
                    <panel childLayout="horizontal" width="100%">
                        <text style="menuTextSmall" text="Marc Trennheuser" textHAlign="left" width="50%" />
                        <text style="menuTextSmall" text="${menu.2768}" textHAlign="right" width="50%"/>
                    </panel>
                    <panel childLayout="horizontal" width="100%">
                        <text style="menuTextSmall" text="Melanie Bongartz" textHAlign="left" width="50%" />
                        <text style="menuTextSmall" text="${menu.2768}" textHAlign="right" width="50%"/>
                    </panel>
                    <panel childLayout="horizontal" width="100%">
                        <text style="menuTextSmall" text="Bernd Reinartz" textHAlign="left" width="50%" />
                        <text style="menuTextSmall" text="${menu.2768}" textHAlign="right" width="50%"/>
                    </panel>
                    <panel childLayout="horizontal" width="100%">
                        <text style="menuTextSmall" text="Anne Vaganay" textHAlign="left" width="50%" />
                        <text style="menuTextSmall" text="${menu.2768}" textHAlign="right" width="50%"/>
                    </panel>
                    <panel childLayout="horizontal" width="100%">
                        <text style="menuTextSmall" text="Stephanie Michel" textHAlign="left" width="50%" />
                        <text style="menuTextSmall" text="${menu.2768}" textHAlign="right" width="50%"/>
                    </panel>
                    <panel childLayout="horizontal" width="100%">
                        <text style="menuTextSmall" text="Karine Dognin" textHAlign="left" width="50%" />
                        <text style="menuTextSmall" text="${menu.423}" textHAlign="right" width="50%"/>
                    </panel>
                    <panel childLayout="horizontal" width="100%">
                        <text style="menuTextSmall" text="Pauline Vivet" textHAlign="left" width="50%" />
                        <text style="menuTextSmall" text="${menu.423}" textHAlign="right" width="50%"/>
                    </panel>
                    <panel childLayout="horizontal" width="100%">
                        <text style="menuTextSmall" text="Chris Plummer" textHAlign="left" width="50%" />
                        <text style="menuTextSmall" text="${menu.423}" textHAlign="right" width="50%"/>
                    </panel>
                    <panel childLayout="horizontal" width="100%">
                        <text style="menuTextSmall" text="Jonathan Harris" textHAlign="left" width="50%" />
                        <text style="menuTextSmall" text="${menu.423}" textHAlign="right" width="50%"/>
                    </panel>
                    <text style="menuTextSmall" text="" width="100%" />
                    <panel childLayout="horizontal" width="100%">
                        <text style="menuTextSmall" text="Carol Aggett" textHAlign="left" width="50%" />
                        <text style="menuTextSmall" text="${menu.407}" textHAlign="right" width="50%"/>
                    </panel>
                    <text style="menuTextSmall" text="" width="100%" />
                    <panel childLayout="horizontal" width="100%">
                        <text style="menuTextSmall" text="${menu.429}" textHAlign="left" width="50%" />
                    </panel>
                    <panel childLayout="horizontal" width="100%">
                        <text style="menuTextSmall" text="Animare &amp; Slash" textHAlign="left" width="50%" />
                    </panel>
                    <panel childLayout="horizontal" width="100%">
                        <text style="menuTextSmall" text="Johan Danforth" textHAlign="left" width="50%" />
                    </panel>
                    <panel childLayout="horizontal" width="100%">
                        <text style="menuTextSmall" text="Richard Wilson" textHAlign="left" width="50%" />
                    </panel>
                    <panel childLayout="horizontal" width="100%">
                        <text style="menuTextSmall" text="Stan Ragan" textHAlign="left" width="50%" />
                    </panel>
                    <panel childLayout="horizontal" width="100%">
                        <text style="menuTextSmall" text="Brian Bonislawsky" textHAlign="left" width="50%" />
                    </panel>

                    <effect>
                        <onActive name="autoScroll" length="70000" start="0" end="-8500" inherit="true" onEndEffect="restartCredits()" />
                    </effect>
                </panel>
            </panel>
            <panel childLayout="center" align="right" valign="bottom">
                <control click="doTransition(266,extras,261)" id="back" name="okButton" />
            </panel>
        </layer>
    </screen>

    <!-- +++++++++++++++++++++++++++++++++++++++ -->
    <!-- Multi player game -->
    <!-- +++++++++++++++++++++++++++++++++++++++ -->
    <screen id="multiplayer" controller="toniarts.openkeeper.game.state.MainMenuState">
        <layer id="layer" childLayout="vertical">
            <panel id="panel1" height="27.9%" width="100%" childLayout="vertical">
                <panel childLayout="center" align="center" valign="center">
                    <text id="multiplayerTitle" style="menuTitleText" text="${menu.149}" />
                </panel>
            </panel>

            <panel id="panel2" height="*" width="100%" align="center" valign="center" childLayout="center" visibleToMouse="true">
                <text style="menuTextSmall" text="Not ready yet" />
            </panel>

            <panel childLayout="horizontal" align="right" valign="bottom">
                <control click="doTransition(272,start,274)" id="back" name="cancelButton" />
                <control id="ok" name="okButton" />
            </panel>
        </layer>
    </screen>

    <!-- +++++++++++++++++++++++++++++++++++++++ -->
    <!-- MPD -->
    <!-- +++++++++++++++++++++++++++++++++++++++ -->
    <screen id="myPetDungeon" controller="toniarts.openkeeper.game.state.MainMenuState">
        <layer id="layer" childLayout="vertical">
            <panel id="panel1" height="12%" width="100%" childLayout="vertical">
                <panel childLayout="center" align="center" valign="center">
                    <text id="myPetDungeonTitle" style="menuTitleText" text="${menu.1675}" />
                </panel>
            </panel>

            <panel id="mpdList" height="*" width="100%" align="center" valign="center" childLayout="vertical" visibleToMouse="true" padding="10px">
                <text style="menuText" text="${mpd1.0}" align="center">
                    <interact onClick="selectMPDLevel(1)" />
                </text>
                <text style="menuText" text="${mpd2.0}" align="center">
                    <interact onClick="selectMPDLevel(2)" />
                </text>
                <text style="menuText" text="${mpd3.0}" align="center">
                    <interact onClick="selectMPDLevel(3)" />
                </text>
                <text style="menuText" text="${mpd4.0}" align="center">
                    <interact onClick="selectMPDLevel(4)" />
                </text>
                <text style="menuText" text="${mpd5.0}" align="center">
                    <interact onClick="selectMPDLevel(5)" />
                </text>
                <text style="menuText" text="${mpd6.0}" align="center">
                    <interact onClick="selectMPDLevel(6)" />
                </text>
                <!-- TODO -->
                <text style="menuText" text="${menu.1618}" align="center"/>
            </panel>

            <panel childLayout="horizontal" align="right" valign="bottom">
                <control click="doTransition(263,start,274)" id="back" name="cancelButton" />
                <text style="menuText" text="" width="48px" margin="5px" />
            </panel>
        </layer>
    </screen>

    <!-- +++++++++++++++++++++++++++++++++++++++ -->
    <!-- Skirmish (& also MP with changes) level selection -->
    <!-- +++++++++++++++++++++++++++++++++++++++ -->
    <screen id="skirmish" controller="toniarts.openkeeper.game.state.MainMenuState">
        <layer id="layer" childLayout="vertical">
            <panel id="panel1" width="100%" childLayout="vertical">
                <panel width="100%" childLayout="center" align="center" valign="center">
                    <text id="skirmishTitle" style="menuTitleText" text="${menu.141}" />
                </panel>

                <!--Spacer-->
                <panel height="5%" width="100%" childLayout="center" align="center" valign="center">
                </panel>

                <!--Two panels, left the game stuff, right the map selection stuff-->
                <panel id="skirmishPanel" width="95%" childLayout="horizontal" align="center" valign="center">

                    <panel id="playersPanel" width="66%" childLayout="vertical" align="center" valign="center" paddingRight="5%">
                        <control id="playersTable" name="table" vertical="optional" displayItems="4" selection="Single"
                                 colCount="5"
                                 col0="${menu.1688};34;java.lang.String;#32050c30"
                                 col1=";33;java.lang.String;#32050c30"
                                 col2=";11;java.lang.String;#00752430"
                                 col3=";11;java.lang.String;#00779e30"
                                 col4=";11;java.lang.String;#00752430"
                        />
                    </panel>
                    <panel width="*" childLayout="vertical" align="center" valign="top">
                        <panel backgroundColor="#f508" width="100%" childLayout="center" marginBottom="8px" valign="top">
                            <control name="label" align="center" valign="top" id="mapNameTitle" style="menuText" />
                        </panel>
                        <panel width="100%" childLayout="horizontal" valign="center" align="center">
                            <text style="menuText" text="${menu.1492}" />
                            <control name="label" id="playerCount" style="menuText" />
                        </panel>
                        <panel width="100%" childLayout="center" valign="center">
                            <image valign="center" align="center" id="mapImage" />
                        </panel>
                    </panel>

                </panel>

                <!--Two panels, left the game stuff, right the map selection stuff-->
                <panel id="skirmishPanel" width="95%" childLayout="horizontal" align="center" valign="center">

                    <panel id="playersPanel" width="66%" childLayout="vertical" align="center" valign="center" paddingRight="5%">
                        <panel width="100%" childLayout="horizontal">
                            <panel width="50%" childLayout="vertical">
                                <text style="menuText" text="${menu.270}" align="left">
                                    <!--<interact onClick="selectMPDLevel(6)" />-->
                                </text>
                            </panel>
                            <panel width="50%" childLayout="vertical">
                                <text style="menuText" text="${menu.2121}" align="center">
                                    <!--<interact onClick="selectMPDLevel(6)" />-->
                                </text>
                                <text style="menuText" text="${menu.1547}" align="center">
                                </text>
                            </panel>
                        </panel>
                    </panel>
                    <panel width="*" childLayout="vertical" align="center" valign="top">
                        <panel width="100%" childLayout="vertical" align="center" valign="top">
                            <text style="menuText" text="${menu.1495}" align="center">
                                <interact onClick="selectMap(skirmish)" />
                            </text>
                            <text style="menuText" text="${menu.1496}" align="center">
                                <interact onClick="selectRandomSkirmishMap()" />
                            </text>
                            <text style="menuText" text="${menu.2803}" align="center">
                            </text>
                        </panel>
                    </panel>

                </panel>

                <!--Spacer-->
                <panel height="3%" width="100%" childLayout="center" align="center" valign="center">

                </panel>
            </panel>
            <panel childLayout="horizontal" align="right" valign="bottom">
                <control click="doTransition(272,singlePlayer,274)" id="back" name="cancelButton" />
                <control click="startSkirmishLevel()" id="start" name="okButton" />
            </panel>
        </layer>
    </screen>

    <!-- +++++++++++++++++++++++++++++++++++++++ -->
    <!-- Map selection -->
    <!-- +++++++++++++++++++++++++++++++++++++++ -->
    <screen id="skirmishMapSelect" controller="toniarts.openkeeper.game.state.MainMenuState">
        <layer id="layer" childLayout="vertical">
            <panel id="panel1" width="100%" childLayout="vertical">
                <panel width="100%" childLayout="center" align="center" valign="center">
                    <text id="skirmishTitle" style="menuTitleText" text="${menu.2800}" />
                </panel>

                <!--Spacer-->
                <panel height="5%" width="100%" childLayout="center" align="center" valign="center">
                </panel>

                <!--Two panels, left the game stuff, right the map selection stuff-->
                <panel id="skirmishPanel" width="95%" childLayout="horizontal" align="center" valign="center">

                    <panel id="mapsPanel" width="66%" childLayout="vertical" align="center" valign="center" paddingRight="5%">
                        <control id="mapsTable" name="table" vertical="optional" displayItems="8" selection="Single" forceSelection="true"
                                 colCount="3"
                                 col0="${menu.1544};50;java.lang.String;#32050c30"
                                 col1="${menu.2960};25;java.lang.String;#32050c30"
                                 col2="${menu.1545};25;java.lang.String;#00752430"
                        />
                    </panel>
                    <panel width="*" childLayout="vertical" align="center" valign="top">
                        <panel backgroundColor="#f508" width="100%" childLayout="center" marginBottom="8px" valign="top">
                            <control name="label" align="center" valign="top" id="mapNameTitle" style="menuText" />
                        </panel>
                        <panel width="100%" childLayout="horizontal" valign="center" align="center">
                            <text style="menuText" text="${menu.1492}" />
                            <control name="label" id="playerCount" style="menuText" />
                        </panel>
                        <panel width="100%" childLayout="center" valign="center">
                            <image valign="center" align="center" id="mapImage" />
                        </panel>
                        <panel width="100%" childLayout="center" valign="center" align="center">
                            <control name="label" id="mapSize" style="menuText" />
                        </panel>
                    </panel>

                </panel>

                <!--Spacer-->
                <panel height="3%" width="100%" childLayout="center" align="center" valign="center">

                </panel>
            </panel>
            <panel childLayout="horizontal" align="right" valign="bottom">
                <control click="cancelMapSelection()" id="back" name="cancelButton" />
                <control click="mapSelected()" id="start" name="okButton" />
            </panel>
        </layer>
    </screen>
</nifty>
